{"Jobs":[{"Name":"J1","Processing":15,"Remaining":15},{"Name":"J2","Processing":24,"Remaining":24},{"Name":"J3","Processing":21,"Remaining":21},{"Name":"J4","Processing":24,"Remaining":24},{"Name":"J5","Processing":22,"Remaining":22},{"Name":"J6","Processing":18,"Remaining":18},{"Name":"J7","Processing":8,"Remaining":8},{"Name":"J8","Processing":3,"Remaining":3},{"Name":"J9","Processing":22,"Remaining":22},{"Name":"J10","Processing":20,"Remaining":20}],"Machines":[{"Name":"M1","Windows":[{"Name":"W11","StartTime":0,"Capacity":11,"Remaining":11,"SubJobs":[]},{"Name":"W12","StartTime":11,"Capacity":11,"Remaining":11,"SubJobs":[]},{"Name":"W13","StartTime":22,"Capacity":3,"Remaining":3,"SubJobs":[]},{"Name":"W14","StartTime":25,"Capacity":8,"Remaining":8,"SubJobs":[]},{"Name":"W15","StartTime":33,"Capacity":10,"Remaining":10,"SubJobs":[]},{"Name":"W16","StartTime":43,"Capacity":12,"Remaining":12,"SubJobs":[]},{"Name":"W17","StartTime":55,"Capacity":5,"Remaining":5,"SubJobs":[]},{"Name":"W18","StartTime":60,"Capacity":99999,"Remaining":99999,"SubJobs":[]}]},{"Name":"M2","Windows":[{"Name":"W21","StartTime":0,"Capacity":9,"Remaining":9,"SubJobs":[]},{"Name":"W22","StartTime":9,"Capacity":5,"Remaining":5,"SubJobs":[]},{"Name":"W23","StartTime":14,"Capacity":7,"Remaining":7,"SubJobs":[]},{"Name":"W24","StartTime":21,"Capacity":6,"Remaining":6,"SubJobs":[]},{"Name":"W25","StartTime":27,"Capacity":7,"Remaining":7,"SubJobs":[]},{"Name":"W26","StartTime":34,"Capacity":11,"Remaining":11,"SubJobs":[]},{"Name":"W27","StartTime":45,"Capacity":6,"Remaining":6,"SubJobs":[]},{"Name":"W28","StartTime":51,"Capacity":8,"Remaining":8,"SubJobs":[]},{"Name":"W29","StartTime":59,"Capacity":99999,"Remaining":99999,"SubJobs":[]}]},{"Name":"M3","Windows":[{"Name":"W31","StartTime":0,"Capacity":4,"Remaining":4,"SubJobs":[]},{"Name":"W32","StartTime":4,"Capacity":5,"Remaining":5,"SubJobs":[]},{"Name":"W33","StartTime":9,"Capacity":10,"Remaining":10,"SubJobs":[]},{"Name":"W34","StartTime":19,"Capacity":7,"Remaining":7,"SubJobs":[]},{"Name":"W35","StartTime":26,"Capacity":3,"Remaining":3,"SubJobs":[]},{"Name":"W36","StartTime":29,"Capacity":7,"Remaining":7,"SubJobs":[]},{"Name":"W37","StartTime":36,"Capacity":3,"Remaining":3,"SubJobs":[]},{"Name":"W38","StartTime":39,"Capacity":7,"Remaining":7,"SubJobs":[]},{"Name":"W39","StartTime":46,"Capacity":3,"Remaining":3,"SubJobs":[]},{"Name":"W310","StartTime":49,"Capacity":3,"Remaining":3,"SubJobs":[]},{"Name":"W311","StartTime":52,"Capacity":10,"Remaining":10,"SubJobs":[]},{"Name":"W312","StartTime":62,"Capacity":99999,"Remaining":99999,"SubJobs":[]}]}],"Splitmin":3,"Optimal":0}